{
  "indexes": [],
  "fieldOverrides": [
    {
      "collectionGroup": "products",
      "fieldPath": "slug",
      "indexes": [
        { "order": "ASCENDING", "queryScope": "COLLECTION_GROUP" }
      ]
    },
    {
      "collectionGroup": "products",
      "fieldPath": "category",
      "indexes": [
        { "order": "ASCENDING", "queryScope": "COLLECTION_GROUP" }
      ]
    },
    {
      "collectionGroup": "products",
      "fieldPath": "group",
      "indexes": [
        { "order": "ASCENDING", "queryScope": "COLLECTION_GROUP" }
      ]
    },
    {
      "collectionGroup": "products",
      "fieldPath": "deleted",
      "indexes": [
        { "order": "ASCENDING", "queryScope": "COLLECTION_GROUP" }
      ]
    }
  ]
}
